Metadata-Version: 2.1
Name: odoo14-addon-auth-api-key-group
Version: 14.0.1.1.1
Summary: Allow grouping API keys together. Grouping per se does nothing. This feature is supposed to be used by other modules to limit access to services or records based on groups of keys.
Home-page: https://github.com/OCA/server-auth
Author: Camptocamp,Odoo Community Association (OCA)
Author-email: support@odoo-community.org
License: LGPL-3
Platform: UNKNOWN
Classifier: Programming Language :: Python
Classifier: Framework :: Odoo
Classifier: Framework :: Odoo :: 14.0
Classifier: License :: OSI Approved :: GNU Lesser General Public License v3 (LGPLv3)
Classifier: Development Status :: 4 - Beta
Requires-Python: >=3.6
Requires-Dist: odoo14-addon-auth-api-key
Requires-Dist: odoo (<14.1dev,>=14.0a)
